safeline/__init__.py
safeline-0.0.7.dist-info/licenses/LICENSE
safeline-0.0.7.dist-info/METADATA
safeline-0.0.7.dist-info/WHEEL
safeline-0.0.7.dist-info/top_level.txt
safeline-0.0.7.dist-info/RECORD
