Metadata-Version: 2.4
Name: safeline
Version: 0.0.7
Summary: A simple SDK for SafeLine CE.
Author-email: AlliotTech <alliot@iots.vip>
Project-URL: Homepage, https://github.com/AlliotTech/python-safeline
Project-URL: Issues, https://github.com/AlliotTech/python-safeline/issues
Keywords: waf,safeline
Classifier: Programming Language :: Python :: 3
Classifier: License :: OSI Approved :: MIT License
Classifier: Operating System :: OS Independent
Requires-Python: >=3.8
License-File: LICENSE
Requires-Dist: requests
Requires-Dist: pyotp
Dynamic: license-file
